<?xml version="1.0" encoding="UTF-8" ?>
<fiche_emploi_metier>
<type_fiche>2</type_fiche>
<libelle_type_fiche>priorise</libelle_type_fiche>
<version_SI>
<version_rome>330</version_rome>
<date_version_si>01/12/2016</date_version_si>
<mois_version_si>D&#0233;cembre</mois_version_si>
<annee_version_si>2016</annee_version_si>
</version_SI>
<bloc_code_rome>
<code_rome>L1502</code_rome>
<intitule>Costume et habillage spectacle</intitule>
<code_ogr>448</code_ogr>
<riasec_majeur>R</riasec_majeur>
<riasec_mineur>a</riasec_mineur>
</bloc_code_rome>
<bloc_appellation nbItemAppellation="12">
<item_app>
<code_ogr>11216</code_ogr>
<libelle>Assistant costumier / Assistante costumi&#0232;re</libelle>
<libelle_court>Assistant costumier / Assistante costumi&#0232;re</libelle_court>
<priorisation>1</priorisation>
</item_app>
<item_app>
<code_ogr>12017</code_ogr>
<libelle>Chef costumier / costumi&#0232;re</libelle>
<libelle_court>Chef costumier / costumi&#0232;re</libelle_court>
<priorisation>1</priorisation>
</item_app>
<item_app>
<code_ogr>12570</code_ogr>
<libelle>Chef habilleur / habilleuse</libelle>
<libelle_court>Chef habilleur / habilleuse</libelle_court>
<priorisation>1</priorisation>
</item_app>
<item_app>
<code_ogr>12815</code_ogr>
<libelle>Concepteur / Conceptrice de costumes</libelle>
<libelle_court>Concepteur / Conceptrice de costumes</libelle_court>
<priorisation>1</priorisation>
</item_app>
<item_app>
<code_ogr>13760</code_ogr>
<libelle>Costumier / Costumi&#0232;re</libelle>
<libelle_court>Costumier / Costumi&#0232;re</libelle_court>
<priorisation>1</priorisation>
</item_app>
<item_app>
<code_ogr>13761</code_ogr>
<libelle>Costumier-habilleur / Costumi&#0232;re-habilleuse</libelle>
<libelle_court>Costumier-habilleur / Costumi&#0232;re-habilleuse</libelle_court>
<priorisation>1</priorisation>
</item_app>
<item_app>
<code_ogr>13762</code_ogr>
<libelle>Costumier-r&#0233;alisateur / Costumi&#0232;re-r&#0233;alisatrice</libelle>
<libelle_court>Costumier-r&#0233;alisateur / Costumi&#0232;re-r&#0233;alisatrice</libelle_court>
<priorisation>1</priorisation>
</item_app>
<item_app>
<code_ogr>13819</code_ogr>
<libelle>Couturier / Couturi&#0232;re spectacle</libelle>
<libelle_court>Couturier / Couturi&#0232;re spectacle</libelle_court>
<priorisation>1</priorisation>
</item_app>
<item_app>
<code_ogr>13833</code_ogr>
<libelle>Cr&#0233;ateur / Cr&#0233;atrice de costumes</libelle>
<libelle_court>Cr&#0233;ateur / Cr&#0233;atrice de costumes</libelle_court>
<priorisation>1</priorisation>
</item_app>
<item_app>
<code_ogr>13911</code_ogr>
<libelle>D&#0233;corateur-costumier / D&#0233;coratrice-costumi&#0232;re</libelle>
<libelle_court>D&#0233;corateur-costumier / D&#0233;coratrice-costumi&#0232;re</libelle_court>
<priorisation>1</priorisation>
</item_app>
<item_app>
<code_ogr>15462</code_ogr>
<libelle>Habilleur / Habilleuse</libelle>
<libelle_court>Habilleur / Habilleuse</libelle_court>
<priorisation>1</priorisation>
</item_app>
<item_app>
<code_ogr>18402</code_ogr>
<libelle>R&#0233;gisseur / R&#0233;gisseuse costumes</libelle>
<libelle_court>R&#0233;gisseur / R&#0233;gisseuse costumes</libelle_court>
<priorisation>1</priorisation>
</item_app>
</bloc_appellation>
<definition nbItemDefinition="3">
Fabrique et entretient les costumes (contemporains, historiques, grotesques) pour des spectacles, des tournages selon les imp&#0233;ratifs de la production. Habille des interpr&#0232;tes (com&#0233;diens, chanteurs, danseurs, ...), des intervenants (pr&#0233;sentateurs, animateurs, ...), des mannequins selon la chronologie des tournages, des spectacles, des d&#0233;fil&#0233;s.
Peut concevoir des costumes.
Peut coordonner une &#0233;quipe.
</definition>
<acces_emploi_metier nbItemAccesEmploiMetier="3">
Cet emploi/m&#0233;tier est accessible avec un dipl&#0244;me de niveau CAP/BEP &#0224; Bac (Bac professionnel, ...) en couture et mode.
Il est &#0233;galement accessible avec une exp&#0233;rience professionnelle en couture sans dipl&#0244;me particulier.
Les recrutements sont ouverts sur contrats de travail &#0224; dur&#0233;e d&#0233;termin&#0233;e d&#0039;usage ou sur vacation, parfois sur contrats de travail &#0224; dur&#0233;e ind&#0233;termin&#0233;e pour les structures permanentes.
</acces_emploi_metier>
<condition_exercice_activite nbItemConditionExercice="5">
L&#0039;activit&#0233; de cet emploi/m&#0233;tier s&#0039;exerce au sein de salles de spectacles, d&#0039;entreprises artisanales, de soci&#0233;t&#0233;s de production de spectacles, ...en relation avec diff&#0233;rentes &#0233;quipes techniques (d&#0233;cor, maquillage, &#0233;clairage, ...), parfois en contact avec le r&#0233;alisateur, le metteur en sc&#0232;ne, le producteur.
Elle peut impliquer des d&#0233;placements (tourn&#0233;es, tournages, ...) et un &#0233;loignement du domicile de plusieurs jours.
Elle varie selon les caract&#0233;ristiques du projet (nombre et type de costumes, genre du spectacle, du film, ...).
Elle peut s&#0039;exercer en horaires d&#0233;cal&#0233;s, les fins de semaine, jours f&#0233;ri&#0233;s, en soir&#0233;e.
L&#0039;activit&#0233; s&#0039;effectue en atelier, en coulisses, en loge et peut impliquer la manipulation de charges.
</condition_exercice_activite>
<bloc_environnement_de_travail nbItemEnvTrav="14">
<item_env>
<code_ogr>23737</code_ogr>
<libelle>Cabaret</libelle>
<code_type_section_env>1</code_type_section_env>
<priorisation>1</priorisation>
</item_env>
<item_env>
<code_ogr>23805</code_ogr>
<libelle>Cirque</libelle>
<code_type_section_env>1</code_type_section_env>
<priorisation>1</priorisation>
</item_env>
<item_env>
<code_ogr>23821</code_ogr>
<libelle>Compagnie artistique (th&#0233;&#0226;tre, danse, arts de la rue, ...)</libelle>
<code_type_section_env>1</code_type_section_env>
<priorisation>1</priorisation>
</item_env>
<item_env>
<code_ogr>23870</code_ogr>
<libelle>Entreprise artisanale</libelle>
<code_type_section_env>1</code_type_section_env>
<priorisation>1</priorisation>
</item_env>
<item_env>
<code_ogr>24029</code_ogr>
<libelle>Parc de loisirs</libelle>
<code_type_section_env>1</code_type_section_env>
<priorisation>1</priorisation>
</item_env>
<item_env>
<code_ogr>24059</code_ogr>
<libelle>Salle de spectacles</libelle>
<code_type_section_env>1</code_type_section_env>
<priorisation>1</priorisation>
</item_env>
<item_env>
<code_ogr>24086</code_ogr>
<libelle>Soci&#0233;t&#0233; de production audiovisuelle, cin&#0233;matographique</libelle>
<code_type_section_env>1</code_type_section_env>
<priorisation>1</priorisation>
</item_env>
<item_env>
<code_ogr>24087</code_ogr>
<libelle>Soci&#0233;t&#0233; de production de spectacles</libelle>
<code_type_section_env>1</code_type_section_env>
<priorisation>1</priorisation>
</item_env>
<item_env>
<code_ogr>24128</code_ogr>
<libelle>Village vacances</libelle>
<code_type_section_env>1</code_type_section_env>
<priorisation>1</priorisation>
</item_env>
<item_env>
<code_ogr>23409</code_ogr>
<libelle>Audiovisuel</libelle>
<code_type_section_env>2</code_type_section_env>
<priorisation>1</priorisation>
</item_env>
<item_env>
<code_ogr>23441</code_ogr>
<libelle>Cin&#0233;ma</libelle>
<code_type_section_env>2</code_type_section_env>
<priorisation>1</priorisation>
</item_env>
<item_env>
<code_ogr>23562</code_ogr>
<libelle>Mode</libelle>
<code_type_section_env>2</code_type_section_env>
<priorisation>1</priorisation>
</item_env>
<item_env>
<code_ogr>23639</code_ogr>
<libelle>Spectacle vivant</libelle>
<code_type_section_env>2</code_type_section_env>
<priorisation>1</priorisation>
</item_env>
<item_env>
<code_ogr>23652</code_ogr>
<libelle>Tourisme</libelle>
<code_type_section_env>2</code_type_section_env>
<priorisation>1</priorisation>
</item_env>
</bloc_environnement_de_travail>
<bloc_activites_de_base nbBlocActiviteBase="1">
<activites_de_base nbItemActivite_AB="6">
<item_ab>
<code_ogr>125755</code_ogr>
<libelle>R&#0233;aliser manuellement un gabarit, patron</libelle>
<code_type_activite>3</code_type_activite>
<code_type_item_activite>2</code_type_item_activite>
<position_item>1</position_item>
<priorisation>1</priorisation>
<riasec_majeur>R</riasec_majeur>
<riasec_mineur>a</riasec_mineur>
</item_ab>
<item_ab>
<code_ogr>102044</code_ogr>
<libelle>R&#0233;aliser des costumes &#0224; th&#0232;me &#0224; partir d&#0039;un patron, d&#0039;un mod&#0232;le</libelle>
<code_type_activite>3</code_type_activite>
<code_type_item_activite>2</code_type_item_activite>
<position_item>2</position_item>
<priorisation>1</priorisation>
<riasec_majeur>R</riasec_majeur>
<riasec_mineur>a</riasec_mineur>
</item_ab>
<item_ab>
<code_ogr>109209</code_ogr>
<libelle>V&#0233;rifier les costumes et r&#0233;aliser les retouches, les finitions</libelle>
<code_type_activite>3</code_type_activite>
<code_type_item_activite>2</code_type_item_activite>
<position_item>3</position_item>
<priorisation>1</priorisation>
<riasec_majeur>C</riasec_majeur>
</item_ab>
<item_ab>
<code_ogr>109210</code_ogr>
<libelle>Installer les costumes des interpr&#0232;tes dans la loge, selon la chronologie du spectacle</libelle>
<code_type_activite>3</code_type_activite>
<code_type_item_activite>2</code_type_item_activite>
<position_item>4</position_item>
<priorisation>1</priorisation>
<riasec_majeur>C</riasec_majeur>
<riasec_mineur>a</riasec_mineur>
</item_ab>
<item_ab>
<code_ogr>109211</code_ogr>
<libelle>Concevoir les costumes des interpr&#0232;tes d&#0039;un spectacle, d&#0039;un tournage selon les indications (&#0233;poque, sc&#0233;nario, th&#0232;me, ...)</libelle>
<code_type_activite>3</code_type_activite>
<code_type_item_activite>2</code_type_item_activite>
<position_item>5</position_item>
<priorisation>1</priorisation>
<riasec_majeur>A</riasec_majeur>
<riasec_mineur>r</riasec_mineur>
</item_ab>
<item_ab>
<code_ogr>124560</code_ogr>
<libelle>Entretenir un textile</libelle>
<code_type_activite>3</code_type_activite>
<code_type_item_activite>2</code_type_item_activite>
<position_item>6</position_item>
<priorisation>1</priorisation>
<riasec_majeur>R</riasec_majeur>
</item_ab>
</activites_de_base>
<savoir_theorique_et_proceduraux nbItemSTP_AB="11">
<item_ab_stp>
<code_ogr>101107</code_ogr>
<libelle>Techniques de patronage</libelle>
<code_type_competence>1</code_type_competence>
<position_item>1</position_item>
<priorisation>1</priorisation>
</item_ab_stp>
<item_ab_stp>
<code_ogr>101098</code_ogr>
<libelle>Techniques de coupe de textile, cuir</libelle>
<code_type_competence>1</code_type_competence>
<position_item>2</position_item>
<priorisation>1</priorisation>
</item_ab_stp>
<item_ab_stp>
<code_ogr>100753</code_ogr>
<libelle>Couture manuelle</libelle>
<code_type_competence>1</code_type_competence>
<position_item>3</position_item>
<priorisation>1</priorisation>
</item_ab_stp>
<item_ab_stp>
<code_ogr>109214</code_ogr>
<libelle>Techniques de montage des costumes</libelle>
<code_type_competence>1</code_type_competence>
<position_item>4</position_item>
<priorisation>1</priorisation>
</item_ab_stp>
<item_ab_stp>
<code_ogr>101100</code_ogr>
<libelle>Proc&#0233;dures d&#0039;essayage</libelle>
<code_type_competence>1</code_type_competence>
<position_item>5</position_item>
<priorisation>1</priorisation>
</item_ab_stp>
<item_ab_stp>
<code_ogr>109213</code_ogr>
<libelle>Utilisation de machine de confection</libelle>
<code_type_competence>1</code_type_competence>
<position_item>6</position_item>
<priorisation>1</priorisation>
</item_ab_stp>
<item_ab_stp>
<code_ogr>124476</code_ogr>
<libelle>Symboles d&#0039;entretien des textiles</libelle>
<code_type_competence>1</code_type_competence>
<position_item>7</position_item>
<priorisation>1</priorisation>
</item_ab_stp>
<item_ab_stp>
<code_ogr>124473</code_ogr>
<libelle>Produits d&#0039;entretien textile</libelle>
<code_type_competence>1</code_type_competence>
<position_item>8</position_item>
<priorisation>1</priorisation>
</item_ab_stp>
<item_ab_stp>
<code_ogr>101175</code_ogr>
<libelle>Techniques de repassage</libelle>
<code_type_competence>1</code_type_competence>
<position_item>9</position_item>
<priorisation>1</priorisation>
</item_ab_stp>
<item_ab_stp>
<code_ogr>101095</code_ogr>
<libelle>Prise de mesures</libelle>
<code_type_competence>1</code_type_competence>
<position_item>10</position_item>
<priorisation>1</priorisation>
</item_ab_stp>
<item_ab_stp>
<code_ogr>109215</code_ogr>
<libelle>Techniques d&#0039;habillage de l&#0039;artiste</libelle>
<code_type_competence>1</code_type_competence>
<position_item>11</position_item>
<priorisation>1</priorisation>
</item_ab_stp>
</savoir_theorique_et_proceduraux>
<savoir_action nbItemSA_AB="0">
</savoir_action>
</bloc_activites_de_base>
<bloc_activites_specifiques nbBlocActiviteSpecifique="6">
<bloc>
<position_bloc>1</position_bloc>
<activite_specifique nbItemActivite_AS="9">
<item_as>
<code_ogr>125448</code_ogr>
<libelle>Fabriquer des accessoires de jeu</libelle>
<code_type_activite>3</code_type_activite>
<code_type_item_activite>2</code_type_item_activite>
<position_item>1</position_item>
<priorisation>1</priorisation>
<riasec_majeur>R</riasec_majeur>
<riasec_mineur>a</riasec_mineur>
</item_as>
<item_as>
<code_ogr>125450</code_ogr>
<libelle>Adapter des articles chaussants</libelle>
<code_type_activite>3</code_type_activite>
<code_type_item_activite>2</code_type_item_activite>
<position_item>2</position_item>
<priorisation>1</priorisation>
<riasec_majeur>R</riasec_majeur>
<riasec_mineur>a</riasec_mineur>
</item_as>
<item_as>
<code_ogr>125352</code_ogr>
<libelle>Fabriquer des articles chaussants</libelle>
<code_type_activite>3</code_type_activite>
<code_type_item_activite>2</code_type_item_activite>
<position_item>3</position_item>
<priorisation>1</priorisation>
<riasec_majeur>R</riasec_majeur>
</item_as>
<item_as>
<code_ogr>125451</code_ogr>
<libelle>Fabriquer des articles de maroquinerie</libelle>
<code_type_activite>3</code_type_activite>
<code_type_item_activite>2</code_type_item_activite>
<position_item>4</position_item>
<priorisation>1</priorisation>
<riasec_majeur>R</riasec_majeur>
<riasec_mineur>a</riasec_mineur>
</item_as>
<item_as>
<code_ogr>125452</code_ogr>
<libelle>Adapter des articles de maroquinerie</libelle>
<code_type_activite>3</code_type_activite>
<code_type_item_activite>2</code_type_item_activite>
<position_item>5</position_item>
<priorisation>1</priorisation>
<riasec_majeur>R</riasec_majeur>
<riasec_mineur>a</riasec_mineur>
</item_as>
<item_as>
<code_ogr>125453</code_ogr>
<libelle>Adapter des bijoux</libelle>
<code_type_activite>3</code_type_activite>
<code_type_item_activite>2</code_type_item_activite>
<position_item>6</position_item>
<priorisation>1</priorisation>
<riasec_majeur>R</riasec_majeur>
<riasec_mineur>a</riasec_mineur>
</item_as>
<item_as>
<code_ogr>117941</code_ogr>
<libelle>Fa&#0231;onner des articles de bijouterie</libelle>
<code_type_activite>3</code_type_activite>
<code_type_item_activite>2</code_type_item_activite>
<position_item>7</position_item>
<priorisation>1</priorisation>
<riasec_majeur>R</riasec_majeur>
<riasec_mineur>a</riasec_mineur>
</item_as>
<item_as>
<code_ogr>125454</code_ogr>
<libelle>Fabriquer des chapeaux</libelle>
<code_type_activite>3</code_type_activite>
<code_type_item_activite>2</code_type_item_activite>
<position_item>8</position_item>
<priorisation>1</priorisation>
<riasec_majeur>R</riasec_majeur>
<riasec_mineur>a</riasec_mineur>
</item_as>
<item_as>
<code_ogr>125455</code_ogr>
<libelle>Adapter des chapeaux</libelle>
<code_type_activite>3</code_type_activite>
<code_type_item_activite>2</code_type_item_activite>
<position_item>9</position_item>
<priorisation>1</priorisation>
<riasec_majeur>R</riasec_majeur>
<riasec_mineur>a</riasec_mineur>
</item_as>
</activite_specifique>
<savoir_theorique_et_proceduraux nbItemSTP_AS="4">
<item_as_stp>
<code_ogr>109221</code_ogr>
<libelle>D&#0233;coupe de mati&#0232;re (cuir, latex, feutre, ...)</libelle>
<code_type_competence>1</code_type_competence>
<position_item>1</position_item>
<priorisation>1</priorisation>
</item_as_stp>
<item_as_stp>
<code_ogr>124485</code_ogr>
<libelle>Montage et assemblage en chapellerie</libelle>
<code_type_competence>1</code_type_competence>
<position_item>2</position_item>
<priorisation>1</priorisation>
</item_as_stp>
<item_as_stp>
<code_ogr>109223</code_ogr>
<libelle>Styles de costumes (grotesque, contemporain, historique)</libelle>
<code_type_competence>1</code_type_competence>
<position_item>3</position_item>
<priorisation>1</priorisation>
</item_as_stp>
<item_as_stp>
<code_ogr>109224</code_ogr>
<libelle>Terminologie du costume</libelle>
<code_type_competence>1</code_type_competence>
<position_item>4</position_item>
<priorisation>1</priorisation>
</item_as_stp>
</savoir_theorique_et_proceduraux>
<savoir_action nbItemSA_AS="0">
</savoir_action>
</bloc>
<bloc>
<position_bloc>3</position_bloc>
<activite_specifique nbItemActivite_AS="2">
<item_as>
<code_ogr>125339</code_ogr>
<libelle>R&#0233;aliser une maquette de costume</libelle>
<code_type_activite>3</code_type_activite>
<code_type_item_activite>2</code_type_item_activite>
<position_item>1</position_item>
<priorisation>1</priorisation>
<riasec_majeur>C</riasec_majeur>
<riasec_mineur>a</riasec_mineur>
</item_as>
<item_as>
<code_ogr>117243</code_ogr>
<libelle>Etablir un devis</libelle>
<code_type_activite>3</code_type_activite>
<code_type_item_activite>2</code_type_item_activite>
<position_item>2</position_item>
<priorisation>1</priorisation>
<riasec_majeur>C</riasec_majeur>
</item_as>
</activite_specifique>
<savoir_theorique_et_proceduraux nbItemSTP_AS="2">
<item_as_stp>
<code_ogr>101119</code_ogr>
<libelle>Caract&#0233;ristiques des tissus et mati&#0232;res textiles</libelle>
<code_type_competence>1</code_type_competence>
<position_item>1</position_item>
<priorisation>1</priorisation>
</item_as_stp>
<item_as_stp>
<code_ogr>101170</code_ogr>
<libelle>Calcul de m&#0233;trage</libelle>
<code_type_competence>1</code_type_competence>
<position_item>2</position_item>
<priorisation>1</priorisation>
</item_as_stp>
</savoir_theorique_et_proceduraux>
<savoir_action nbItemSA_AS="0">
</savoir_action>
</bloc>
<bloc>
<position_bloc>4</position_bloc>
<activite_specifique nbItemActivite_AS="1">
<item_as>
<code_ogr>126414</code_ogr>
<libelle>D&#0233;finir les conditions de r&#0233;alisation des costumes d&#0039;un spectacle (temps de r&#0233;alisation, moyens, logistique,...)</libelle>
<code_type_activite>3</code_type_activite>
<code_type_item_activite>2</code_type_item_activite>
<position_item>1</position_item>
<priorisation>1</priorisation>
</item_as>
</activite_specifique>
<savoir_theorique_et_proceduraux nbItemSTP_AS="0">
</savoir_theorique_et_proceduraux>
<savoir_action nbItemSA_AS="0">
</savoir_action>
</bloc>
<bloc>
<position_bloc>5</position_bloc>
<activite_specifique nbItemActivite_AS="1">
<item_as>
<code_ogr>115429</code_ogr>
<libelle>Teindre des mati&#0232;res (plume, tissu, fourrure, ...)</libelle>
<code_type_activite>3</code_type_activite>
<code_type_item_activite>2</code_type_item_activite>
<position_item>1</position_item>
<priorisation>1</priorisation>
<riasec_majeur>R</riasec_majeur>
<riasec_mineur>a</riasec_mineur>
</item_as>
</activite_specifique>
<savoir_theorique_et_proceduraux nbItemSTP_AS="1">
<item_as_stp>
<code_ogr>109225</code_ogr>
<libelle>Techniques de teinture des tissus, des mati&#0232;res</libelle>
<code_type_competence>1</code_type_competence>
<position_item>1</position_item>
<priorisation>1</priorisation>
</item_as_stp>
</savoir_theorique_et_proceduraux>
<savoir_action nbItemSA_AS="0">
</savoir_action>
</bloc>
<bloc>
<position_bloc>6</position_bloc>
<activite_specifique nbItemActivite_AS="1">
<item_as>
<code_ogr>125230</code_ogr>
<libelle>D&#0233;corer des costumes par des techniques en trompe l&#0039;oeil</libelle>
<code_type_activite>3</code_type_activite>
<code_type_item_activite>2</code_type_item_activite>
<position_item>1</position_item>
<priorisation>1</priorisation>
<riasec_majeur>A</riasec_majeur>
</item_as>
</activite_specifique>
<savoir_theorique_et_proceduraux nbItemSTP_AS="2">
<item_as_stp>
<code_ogr>109227</code_ogr>
<libelle>Techniques de patine des costumes</libelle>
<code_type_competence>1</code_type_competence>
<position_item>1</position_item>
<priorisation>1</priorisation>
</item_as_stp>
<item_as_stp>
<code_ogr>109226</code_ogr>
<libelle>Techniques de d&#0233;cor des costumes</libelle>
<code_type_competence>1</code_type_competence>
<position_item>2</position_item>
<priorisation>1</priorisation>
</item_as_stp>
</savoir_theorique_et_proceduraux>
<savoir_action nbItemSA_AS="0">
</savoir_action>
</bloc>
<bloc>
<position_bloc>7</position_bloc>
<activite_specifique nbItemActivite_AS="1">
<item_as>
<code_ogr>102359</code_ogr>
<libelle>Coordonner l&#0039;activit&#0233; d&#0039;une &#0233;quipe</libelle>
<code_type_activite>3</code_type_activite>
<code_type_item_activite>2</code_type_item_activite>
<position_item>1</position_item>
<priorisation>1</priorisation>
<riasec_majeur>E</riasec_majeur>
<riasec_mineur>s</riasec_mineur>
</item_as>
</activite_specifique>
<savoir_theorique_et_proceduraux nbItemSTP_AS="2">
<item_as_stp>
<code_ogr>119000</code_ogr>
<libelle>Gestion des stocks et des approvisionnements</libelle>
<code_type_competence>1</code_type_competence>
<position_item>1</position_item>
<priorisation>1</priorisation>
</item_as_stp>
<item_as_stp>
<code_ogr>119842</code_ogr>
<libelle>Management</libelle>
<code_type_competence>1</code_type_competence>
<position_item>2</position_item>
<priorisation>1</priorisation>
</item_as_stp>
</savoir_theorique_et_proceduraux>
<savoir_action nbItemSA_AS="0">
</savoir_action>
</bloc>
</bloc_activites_specifiques>
<bloc_mobilites>
<mobilites_proches nbItemMob="4">
<item_mob_pr><code_type_mobilite>1</code_type_mobilite>
<liste_appellation_source>
<code_appellation_source>0</code_appellation_source>
<libelle_appellation_source>Toutes les appellations</libelle_appellation_source>
</liste_appellation_source>
<code_rome_cible>B1801</code_rome_cible>
<libelle_rome_cible>R&#0233;alisation d&#0039;articles de chapellerie</libelle_rome_cible>
<liste_appellation_cible>
<code_appellation_cible>0</code_appellation_cible>
<libelle_appellation_cible>Toutes les appellations</libelle_appellation_cible>
</liste_appellation_cible>
</item_mob_pr>
<item_mob_pr><code_type_mobilite>1</code_type_mobilite>
<liste_appellation_source>
<code_appellation_source>0</code_appellation_source>
<libelle_appellation_source>Toutes les appellations</libelle_appellation_source>
</liste_appellation_source>
<code_rome_cible>B1803</code_rome_cible>
<libelle_rome_cible>R&#0233;alisation de v&#0234;tements sur mesure ou en petite s&#0233;rie</libelle_rome_cible>
<liste_appellation_cible>
<code_appellation_cible>0</code_appellation_cible>
<libelle_appellation_cible>Toutes les appellations</libelle_appellation_cible>
</liste_appellation_cible>
</item_mob_pr>
<item_mob_pr><code_type_mobilite>1</code_type_mobilite>
<liste_appellation_source>
<code_appellation_source>0</code_appellation_source>
<libelle_appellation_source>Toutes les appellations</libelle_appellation_source>
</liste_appellation_source>
<code_rome_cible>B1805</code_rome_cible>
<libelle_rome_cible>Stylisme</libelle_rome_cible>
<liste_appellation_cible>
<code_appellation_cible>0</code_appellation_cible>
<libelle_appellation_cible>Toutes les appellations</libelle_appellation_cible>
</liste_appellation_cible>
</item_mob_pr>
<item_mob_pr><code_type_mobilite>1</code_type_mobilite>
<liste_appellation_source>
<code_appellation_source>0</code_appellation_source>
<libelle_appellation_source>Toutes les appellations</libelle_appellation_source>
</liste_appellation_source>
<code_rome_cible>D1206</code_rome_cible>
<libelle_rome_cible>R&#0233;paration d&#0039;articles en cuir et mat&#0233;riaux souples</libelle_rome_cible>
<liste_appellation_cible>
<code_appellation_cible>0</code_appellation_cible>
<libelle_appellation_cible>Toutes les appellations</libelle_appellation_cible>
</liste_appellation_cible>
</item_mob_pr>
</mobilites_proches>
<mobilites_si_evolution nbItemMob="1">
<item_mob_ev><code_type_mobilite>2</code_type_mobilite>
<liste_appellation_source>
<code_appellation_source>0</code_appellation_source>
<libelle_appellation_source>Toutes les appellations</libelle_appellation_source>
</liste_appellation_source>
<code_rome_cible>H1205</code_rome_cible>
<libelle_rome_cible>&#0201;tudes - mod&#0232;les en industrie des mat&#0233;riaux souples</libelle_rome_cible>
<liste_appellation_cible>
<code_appellation_cible>0</code_appellation_cible>
<libelle_appellation_cible>Toutes les appellations</libelle_appellation_cible>
</liste_appellation_cible>
</item_mob_ev>
</mobilites_si_evolution>
</bloc_mobilites>
</fiche_emploi_metier>